nonebot_plugin_sentry/__init__.py
nonebot_plugin_sentry/compat.py
nonebot_plugin_sentry/config.py
nonebot_plugin_sentry-2.0.0.dist-info/LICENSE
nonebot_plugin_sentry-2.0.0.dist-info/METADATA
nonebot_plugin_sentry-2.0.0.dist-info/WHEEL
nonebot_plugin_sentry-2.0.0.dist-info/RECORD
