Metadata-Version: 2.1
Name: nonebot-plugin-sentry
Version: 2.0.0
Summary: Push your bot errors to Sentry.io
Home-page: https://github.com/nonebot/plugin-sentry
License: MIT
Keywords: nonebot,nonebot2,sentry
Author: yanyongyu
Author-email: yyy@nonebot.dev
Requires-Python: >=3.9,<4.0
Classifier: License :: OSI Approved :: MIT License
Classifier: Programming Language :: Python :: 3
Classifier: Programming Language :: Python :: 3.9
Classifier: Programming Language :: Python :: 3.10
Classifier: Programming Language :: Python :: 3.11
Classifier: Programming Language :: Python :: 3.12
Requires-Dist: nonebot2 (>=2.2.0,<3.0.0)
Requires-Dist: pydantic (>=1.10.0,<3.0.0,!=2.5.0,!=2.5.1)
Requires-Dist: sentry-sdk[loguru] (>=2.0.0,<3.0.0)
Project-URL: Documentation, https://github.com/nonebot/plugin-sentry#readme
Project-URL: Repository, https://github.com/nonebot/plugin-sentry
